[
  {
    "﻿Thời gian Click": "2025-08-12 14:53:00",
    "Thời Gian Đặt Hàng": "2025-08-12 23:47:10",
    "ID đơn hàng": "250813MU794QYX",
    "Tên Item": "Đũa phanh Dream - đũa thắng sau hàng công ty loại 1",
    "Trạng thái đặt hàng": "Đang chờ xử lý",
    "Giá trị đơn hàng (₫)": 12000.0,
    "Hoa hồng Shopee trên sản phẩm(₫)": "1.080",
    "Chiết Khấu 2%": 240.0
  },
  {
    "﻿Thời gian Click": "2025-08-12 23:13:30",
    "Thời Gian Đặt Hàng": "2025-08-12 23:16:13",
    "ID đơn hàng": "250813MSFX5V6M",
    "Tên Item": "Sách - Xứ Sở Miên Man - Bản Thường và Bản Siêu Đặc Biệt Tặng Kèm Quà - Độc Quyền Fahasa",
    "Trạng thái đặt hàng": "Đang chờ xử lý",
    "Giá trị đơn hàng (₫)": 365000.0,
    "Hoa hồng Shopee trên sản phẩm(₫)": "32.850",
    "Chiết Khấu 2%": 7300.0
  },
  {
    "﻿Thời gian Click": "2025-08-12 15:38:28",
    "Thời Gian Đặt Hàng": "2025-08-12 22:19:28",
    "ID đơn hàng": "250812MPADWYY5",
    "Tên Item": "Zwinz2 Handmade Da Vòng Tay Nhiều Lớp Quấn Vòng Tay Đơn Giản Hợp Kim Khóa Lắc Tay Vintage Dây Đeo Tay Cho Nữ Tôi",
    "Trạng thái đặt hàng": "Đang chờ xử lý",
    "Giá trị đơn hàng (₫)": 100955.0,
    "Hoa hồng Shopee trên sản phẩm(₫)": "9.086",
    "Chiết Khấu 2%": 2019.0
  },
  {
    "﻿Thời gian Click": "2025-08-12 18:44:54",
    "Thời Gian Đặt Hàng": "2025-08-12 20:52:18",
    "ID đơn hàng": "250812MHEJ7CYV",
    "Tên Item": "Cây Lau Kính Thông Minh 4 Trong 1, Có Phun Sương, Gạt Nước, Thu Nước Bẩn, Cán Nhôm Độ Dài Linh Hoạt Parroti Shiny SN04",
    "Trạng thái đặt hàng": "Đang chờ xử lý",
    "Giá trị đơn hàng (₫)": 252860.0,
    "Hoa hồng Shopee trên sản phẩm(₫)": "22.757",
    "Chiết Khấu 2%": 5057.0
  },
  {
    "﻿Thời gian Click": "2025-08-12 20:26:52",
    "Thời Gian Đặt Hàng": "2025-08-12 20:36:39",
    "ID đơn hàng": "250812MGJKMK9F",
    "Tên Item": "Cảm biến lùi 4 mắt, cảnh báo va chạm Ô tô đủ 3 màu cơ bản đen bạc trắng",
    "Trạng thái đặt hàng": "Đang chờ xử lý",
    "Giá trị đơn hàng (₫)": 147599.0,
    "Hoa hồng Shopee trên sản phẩm(₫)": "13.284",
    "Chiết Khấu 2%": 2952.0
  },
  {
    "﻿Thời gian Click": "2025-08-09 22:20:45",
    "Thời Gian Đặt Hàng": "2025-08-12 20:23:22",
    "ID đơn hàng": "250812MFTUJY46",
    "Tên Item": "Đũa ăn gỗ Kim Giao rừng Cúc Phương Ninh Bình chính hãng loại 1 chống mốc không mối mọt không cong vênh chịu nhiệt tốt",
    "Trạng thái đặt hàng": "Đang chờ xử lý",
    "Giá trị đơn hàng (₫)": 238000.0,
    "Hoa hồng Shopee trên sản phẩm(₫)": "21.420",
    "Chiết Khấu 2%": 4760.0
  },
  {
    "﻿Thời gian Click": "2025-08-12 20:14:47",
    "Thời Gian Đặt Hàng": "2025-08-12 20:20:01",
    "ID đơn hàng": "250812MFMUWB74",
    "Tên Item": "Dép Cá Hề, Dép Cá Mập Đi Trong Nhà Giá Rẻ Mẫu Mới 2024",
    "Trạng thái đặt hàng": "Đang chờ xử lý",
    "Giá trị đơn hàng (₫)": 50490.0,
    "Hoa hồng Shopee trên sản phẩm(₫)": "4.544",
    "Chiết Khấu 2%": 1010.0
  },
  {
    "﻿Thời gian Click": "2025-08-12 18:18:05",
    "Thời Gian Đặt Hàng": "2025-08-12 18:41:53",
    "ID đơn hàng": "250812MA5CPNVS",
    "Tên Item": "Máy Hút Bụi Diệt Khuẩn UV Mi.Mijia MJCMY01DY Gen 1 - Mijia Gen 2 MJCMY02DY- BH 6 tháng",
    "Trạng thái đặt hàng": "Đang chờ xử lý",
    "Giá trị đơn hàng (₫)": 727000.0,
    "Hoa hồng Shopee trên sản phẩm(₫)": "50.000",
    "Chiết Khấu 2%": 14540.0
  },
  {
    "﻿Thời gian Click": "2025-08-12 13:15:58",
    "Thời Gian Đặt Hàng": "2025-08-12 18:01:55",
    "ID đơn hàng": "250812M7WWQGPJ",
    "Tên Item": "Dây Kháng Lực Miniband AoLikes Version 2024 Tập Mông Đá Bóng Yoga Cao Su Cao Cấp",
    "Trạng thái đặt hàng": "Đang chờ xử lý",
    "Giá trị đơn hàng (₫)": 25000.0,
    "Hoa hồng Shopee trên sản phẩm(₫)": "2.250",
    "Chiết Khấu 2%": 500.0
  },
  {
    "﻿Thời gian Click": "2025-08-12 05:07:30",
    "Thời Gian Đặt Hàng": "2025-08-12 17:26:08",
    "ID đơn hàng": "250812M5WW9TEV",
    "Tên Item": "Phấn Diệt Kiến, Gián Vipesco (gói 50 gr) Bột Trừ Kiến Tận Gốc, Hiệu Quả Nhanh - Hạt giống Rạng Đông",
    "Trạng thái đặt hàng": "Đang chờ xử lý",
    "Giá trị đơn hàng (₫)": 25211.0,
    "Hoa hồng Shopee trên sản phẩm(₫)": "2.269",
    "Chiết Khấu 2%": 504.0
  },
  {
    "﻿Thời gian Click": "2025-08-12 05:07:30",
    "Thời Gian Đặt Hàng": "2025-08-12 17:26:08",
    "ID đơn hàng": "250812M5WW9TEV",
    "Tên Item": "[10 lọ] Diệt Kiến Gián Sinh Học 10ml - Diệt kiến gián tận gốc an toàn cho thú cưng, hiểu quả nhanh - Hạt giống Rạng Đông",
    "Trạng thái đặt hàng": "Đang chờ xử lý",
    "Giá trị đơn hàng (₫)": 23489.0,
    "Hoa hồng Shopee trên sản phẩm(₫)": "2.114",
    "Chiết Khấu 2%": 470.0
  },
  {
    "﻿Thời gian Click": "2025-08-11 15:12:39",
    "Thời Gian Đặt Hàng": "2025-08-12 15:42:37",
    "ID đơn hàng": "250812M04TWT09",
    "Tên Item": "Đèn tường, đèn vách trang trí hiện đại phòng khách, phòng ngủ, hành lang HY812",
    "Trạng thái đặt hàng": "Đang chờ xử lý",
    "Giá trị đơn hàng (₫)": 152100.0,
    "Hoa hồng Shopee trên sản phẩm(₫)": "8.767",
    "Chiết Khấu 2%": 3042.0
  },
  {
    "﻿Thời gian Click": "2025-08-11 15:12:39",
    "Thời Gian Đặt Hàng": "2025-08-12 15:42:37",
    "ID đơn hàng": "250812M04TWT09",
    "Tên Item": "Đèn ngủ LED gắn tường 6W hình chữ nhật phong cách tối giản",
    "Trạng thái đặt hàng": "Đang chờ xử lý",
    "Giá trị đơn hàng (₫)": 429300.0,
    "Hoa hồng Shopee trên sản phẩm(₫)": "24.740",
    "Chiết Khấu 2%": 8586.0
  },
  {
    "﻿Thời gian Click": "2025-08-11 15:12:39",
    "Thời Gian Đặt Hàng": "2025-08-12 15:42:37",
    "ID đơn hàng": "250812M04TWT09",
    "Tên Item": "Đèn thả bàn ăn cao cấp 3 bóng sơn tĩnh điện YAHINO",
    "Trạng thái đặt hàng": "Đang chờ xử lý",
    "Giá trị đơn hàng (₫)": 286200.0,
    "Hoa hồng Shopee trên sản phẩm(₫)": "16.493",
    "Chiết Khấu 2%": 5724.0
  },
  {
    "﻿Thời gian Click": "2025-08-12 13:19:40",
    "Thời Gian Đặt Hàng": "2025-08-12 15:06:01",
    "ID đơn hàng": "250812KX3CQD3M",
    "Tên Item": "Muối Kokomi Bóc Từ Mì Gói – Gia Vị Nấu Ăn, Nêm Nếm Đa Dụng",
    "Trạng thái đặt hàng": "Đang chờ xử lý",
    "Giá trị đơn hàng (₫)": 42750.0,
    "Hoa hồng Shopee trên sản phẩm(₫)": "3.848",
    "Chiết Khấu 2%": 855.0
  },
  {
    "﻿Thời gian Click": "2025-08-12 12:25:32",
    "Thời Gian Đặt Hàng": "2025-08-12 14:55:47",
    "ID đơn hàng": "250812KWH34VSF",
    "Tên Item": "Balo nữ đi học thời trang cặp sách nữ đi học dễ thương kèm 3 gấu Ba lô nhiều ngăn chống nước đựng laptop 15 inh KUBO B40",
    "Trạng thái đặt hàng": "Đang chờ xử lý",
    "Giá trị đơn hàng (₫)": 250200.0,
    "Hoa hồng Shopee trên sản phẩm(₫)": "22.518",
    "Chiết Khấu 2%": 5004.0
  },
  {
    "﻿Thời gian Click": "2025-08-11 20:07:55",
    "Thời Gian Đặt Hàng": "2025-08-12 09:51:18",
    "ID đơn hàng": "250812KCGMD3VX",
    "Tên Item": "Vá sạn/ Xẻng đảo lật thức ăn silicone Ggomi GG470 an toàn sức khỏe, 4 màu sắc sặc sỡ dùng để chiên xào, lật nấu thức ăn",
    "Trạng thái đặt hàng": "Đang chờ xử lý",
    "Giá trị đơn hàng (₫)": 117796.0,
    "Hoa hồng Shopee trên sản phẩm(₫)": "10.602",
    "Chiết Khấu 2%": 2356.0
  },
  {
    "﻿Thời gian Click": "2025-08-11 20:07:55",
    "Thời Gian Đặt Hàng": "2025-08-12 09:51:18",
    "ID đơn hàng": "250812KCGMD3VX",
    "Tên Item": "Kẹp gắp thức ăn nhiều loại, kẹp gắp thịt, kẹp gắp đồ nướng inox khổng gi an toàn sử dụng - GGOMI HC goods",
    "Trạng thái đặt hàng": "Đang chờ xử lý",
    "Giá trị đơn hàng (₫)": 64253.0,
    "Hoa hồng Shopee trên sản phẩm(₫)": "5.783",
    "Chiết Khấu 2%": 1285.0
  },
  {
    "﻿Thời gian Click": "2025-08-12 07:39:53",
    "Thời Gian Đặt Hàng": "2025-08-12 07:42:51",
    "ID đơn hàng": "250812K5AXGTKQ",
    "Tên Item": "Sách - Xứ Sở Miên Man",
    "Trạng thái đặt hàng": "Đang chờ xử lý",
    "Giá trị đơn hàng (₫)": 158400.0,
    "Hoa hồng Shopee trên sản phẩm(₫)": "14.256",
    "Chiết Khấu 2%": 3168.0
  }
]